healthsciencecalculator/__init__.py
healthsciencecalculator/get_bmi.py
healthsciencecalculator/get_bmr.py
healthsciencecalculator/get_tdee.py
healthsciencecalculator/unit_convert.py
healthsciencecalculator-0.2.4.dist-info/LICENSE
healthsciencecalculator-0.2.4.dist-info/METADATA
healthsciencecalculator-0.2.4.dist-info/WHEEL
healthsciencecalculator-0.2.4.dist-info/RECORD
