Metadata-Version: 2.3
Name: healthsciencecalculator
Version: 0.2.4
Summary: Calculates basic health indexes
License: MIT
Author: Forgive Agbesi
Author-email: forgiveagbesi7478@gmail.com
Requires-Python: >=3.11,<4
Classifier: License :: OSI Approved :: MIT License
Classifier: Programming Language :: Python :: 3
Classifier: Programming Language :: Python :: 3.11
Classifier: Programming Language :: Python :: 3.12
Classifier: Programming Language :: Python :: 3.13
Requires-Dist: pandas (>=2.2.3)
